{
  "kind": "collectionType",
  "collectionName": "foundations_steps",
  "info": {
    "singularName": "foundations-step",
    "pluralName": "foundations-steps",
    "displayName": "Foundations Step"
  },
  "options": {
    "draftAndPublish": true
  },
  "pluginOptions": {
    "i18n": {
      "localized": true
    }
  },
  "attributes": {
    "title": {
      "pluginOptions": {
        "i18n": {
          "localized": true
        },
        "translate": {
          "translate": "translate"
        }
      },
      "type": "string",
      "required": true
    },
    "description": {
      "pluginOptions": {
        "i18n": {
          "localized": true
        },
        "translate": {
          "translate": "translate"
        }
      },
      "type": "text",
      "required": true
    },
    "icon": {
      "type": "component",
      "repeatable": false,
      "pluginOptions": {
        "i18n": {
          "localized": true
        },
        "translate": {
          "translate": "translate"
        }
      },
      "component": "icon.icon"
    }
  }
}
